conventions/__init__.py
conventions/__main__.py
conventions/cache.py
conventions/cli.py
conventions/conferences.py
conventions/config.py
conventions/search.py
conventions-0.1.1.dist-info/licenses/LICENSE
conventions-0.1.1.dist-info/METADATA
conventions-0.1.1.dist-info/WHEEL
conventions-0.1.1.dist-info/top_level.txt
conventions-0.1.1.dist-info/RECORD
