Metadata-Version: 2.4
Name: conventions
Version: 0.1.1
Summary: A CLI tool to search for conference talks
Home-page: https://github.com/hwranderson/conventions
Author: Henry Anderson
Author-email: hwranderson@gmail.com
License: MIT
Requires-Python: >=3.6
License-File: LICENSE
Dynamic: author
Dynamic: author-email
Dynamic: home-page
Dynamic: license-file
Dynamic: requires-python
